{
  "order": 3,
  "slug": "cafe",
  "parent": {
    "slug": "alimentos-y-bebidas",
    "name": "Alimentos y Bebidas"
  },
  "name": "Café",
  "eyebrow": "Alimentos y Bebidas",
  "hero": {
    "title": "Café",
    "lead": "Humedad, perfil y control de calidad del grano."
  },
  "intro": "Control de calidad del café verde y tostado.",
  "items_title": "Análisis y parámetros típicos",
  "items": [
    {
      "name": "Humedad",
      "desc": "Punto óptimo de tueste y almacenamiento."
    },
    {
      "name": "Cafeína (HPLC)",
      "desc": "Contenido y control de descafeinado."
    },
    {
      "name": "Ocratoxina A",
      "desc": "Micotoxina regulada por HPLC."
    },
    {
      "name": "Metales (ICP)",
      "desc": "Trazas y contaminantes."
    },
    {
      "name": "Perfil sensorial",
      "desc": "Calidad de taza."
    }
  ],
  "meta": {
    "title": "Café | Alimentos y Bebidas | CCV Grupo Venezuela",
    "description": "Humedad, perfil y control de calidad del grano."
  },
  "brands": [
    {
      "name": "PerkinElmer",
      "slug": "perkin-elmer"
    }
  ]
}
