{
  "order": 1,
  "slug": "lims",
  "parent": {
    "slug": "informatica-lims",
    "name": "Informática · LIMS"
  },
  "name": "LIMS",
  "eyebrow": "Informática · LIMS",
  "hero": {
    "title": "LIMS",
    "lead": "Sistema de gestión de información de laboratorio de extremo a extremo."
  },
  "intro": "Soluciones de lims respaldadas por la experiencia y el soporte técnico local de CCV Grupo Venezuela.",
  "items_title": "Soluciones",
  "items": [],
  "meta": {
    "title": "LIMS | Informática · LIMS | CCV Grupo Venezuela",
    "description": "Sistema de gestión de información de laboratorio de extremo a extremo."
  },
  "process_title": "Cómo lo implementamos",
  "process": [
    {
      "icon": "target",
      "title": "Relevamiento",
      "desc": "Mapeamos flujos, equipos y requisitos."
    },
    {
      "icon": "cog",
      "title": "Configuración",
      "desc": "Parametrización e integraciones."
    },
    {
      "icon": "cpu",
      "title": "Integración",
      "desc": "Captura automática desde los instrumentos."
    },
    {
      "icon": "support",
      "title": "Soporte",
      "desc": "Capacitación y soporte continuo."
    }
  ]
}
