{
  "order": 1,
  "slug": "materias-primas",
  "parent": {
    "slug": "industria-quimica",
    "name": "Industria Química"
  },
  "name": "Materias primas",
  "eyebrow": "Industria Química",
  "hero": {
    "title": "Materias primas",
    "lead": "Identidad, pureza y conformidad de insumos."
  },
  "intro": "Identidad, pureza y conformidad de materias primas.",
  "items_title": "Análisis y parámetros típicos",
  "items": [
    {
      "name": "Identificación (FTIR / NIR)",
      "desc": "Verificación de identidad."
    },
    {
      "name": "Pureza cromatográfica",
      "desc": "HPLC / GC."
    },
    {
      "name": "Metales (ICP)",
      "desc": "Contaminantes elementales."
    },
    {
      "name": "Humedad",
      "desc": "Contenido de agua."
    },
    {
      "name": "Punto de fusión / ebullición",
      "desc": "Identidad y pureza."
    }
  ],
  "meta": {
    "title": "Materias primas | Industria Química | CCV Grupo Venezuela",
    "description": "Identidad, pureza y conformidad de insumos."
  },
  "brands": [
    {
      "name": "PerkinElmer",
      "slug": "perkin-elmer"
    }
  ],
  "process_title": "De la muestra al resultado",
  "process": [
    {
      "icon": "vial",
      "title": "Muestreo y recepción",
      "desc": "Recepción, registro e identificación de muestras de materias primas."
    },
    {
      "icon": "prep",
      "title": "Preparación de muestra",
      "desc": "Digestión, extracción o acondicionamiento según el método normalizado."
    },
    {
      "icon": "wave",
      "title": "Análisis instrumental",
      "desc": "Medición con la técnica adecuada y control de calidad de los datos."
    },
    {
      "icon": "report",
      "title": "Resultados e informe",
      "desc": "Validación, reporte de resultados y asesoría técnica."
    }
  ]
}
