{
  "order": 2,
  "slug": "produccion-agricola",
  "parent": {
    "slug": "agroindustria",
    "name": "Agroindustria"
  },
  "name": "Producción agrícola",
  "eyebrow": "Agroindustria",
  "hero": {
    "title": "Producción agrícola",
    "lead": "Análisis de suelos, fertilizantes y agua de riego."
  },
  "intro": "Análisis de suelos, aguas y fertilizantes para producción agrícola.",
  "items_title": "Análisis y parámetros típicos",
  "items": [
    {
      "name": "Fertilidad de suelos",
      "desc": "pH, materia orgánica y CIC."
    },
    {
      "name": "Nutrientes (N-P-K)",
      "desc": "Recomendación de fertilización."
    },
    {
      "name": "Metales (ICP)",
      "desc": "Micronutrientes y contaminantes."
    },
    {
      "name": "Pesticidas",
      "desc": "Residuos por GC-MS / LC-MS."
    },
    {
      "name": "Calidad de agua de riego",
      "desc": "Sales y metales."
    }
  ],
  "meta": {
    "title": "Producción agrícola | Agroindustria | CCV Grupo Venezuela",
    "description": "Análisis de suelos, fertilizantes y agua de riego."
  },
  "brands": [
    {
      "name": "PerkinElmer",
      "slug": "perkin-elmer"
    }
  ],
  "process_title": "De la muestra al resultado",
  "process": [
    {
      "icon": "vial",
      "title": "Muestreo y recepción",
      "desc": "Recepción, registro e identificación de muestras de producción agrícola."
    },
    {
      "icon": "prep",
      "title": "Preparación de muestra",
      "desc": "Digestión, extracción o acondicionamiento según el método normalizado."
    },
    {
      "icon": "wave",
      "title": "Análisis instrumental",
      "desc": "Medición con la técnica adecuada y control de calidad de los datos."
    },
    {
      "icon": "report",
      "title": "Resultados e informe",
      "desc": "Validación, reporte de resultados y asesoría técnica."
    }
  ]
}
